{"nodes": [{"id": "query", "label": "_query.py", "file_type": "code", "source_file": "src\\gradata\\_query.py", "source_location": "L1"}, {"id": "query_ensure_fts_table", "label": "_ensure_fts_table()", "file_type": "code", "source_file": "src\\gradata\\_query.py", "source_location": "L38"}, {"id": "query_fts_index", "label": "fts_index()", "file_type": "code", "source_file": "src\\gradata\\_query.py", "source_location": "L55"}, {"id": "query_fts_index_batch", "label": "fts_index_batch()", "file_type": "code", "source_file": "src\\gradata\\_query.py", "source_location": "L73"}, {"id": "query_fts_rebuild", "label": "fts_rebuild()", "file_type": "code", "source_file": "src\\gradata\\_query.py", "source_location": "L91"}, {"id": "query_fts_search", "label": "fts_search()", "file_type": "code", "source_file": "src\\gradata\\_query.py", "source_location": "L140"}, {"id": "query_detect_query_mode", "label": "detect_query_mode()", "file_type": "code", "source_file": "src\\gradata\\_query.py", "source_location": "L178"}, {"id": "query_reciprocal_rank_fusion", "label": "reciprocal_rank_fusion()", "file_type": "code", "source_file": "src\\gradata\\_query.py", "source_location": "L195"}, {"id": "query_compute_recency_weight", "label": "compute_recency_weight()", "file_type": "code", "source_file": "src\\gradata\\_query.py", "source_location": "L214"}, {"id": "query_classify_confidence", "label": "classify_confidence()", "file_type": "code", "source_file": "src\\gradata\\_query.py", "source_location": "L227"}, {"id": "query_infer_memory_type", "label": "infer_memory_type()", "file_type": "code", "source_file": "src\\gradata\\_query.py", "source_location": "L237"}, {"id": "query_get_memory_weight", "label": "get_memory_weight()", "file_type": "code", "source_file": "src\\gradata\\_query.py", "source_location": "L257"}, {"id": "query_brain_search", "label": "brain_search()", "file_type": "code", "source_file": "src\\gradata\\_query.py", "source_location": "L264"}, {"id": "query_rationale_1", "label": "Brain Query Script \u2014 FTS5 Search.\r ====================================\r Primary", "file_type": "rationale", "source_file": "src\\gradata\\_query.py", "source_location": "L1"}, {"id": "query_rationale_270", "label": "Search the brain using FTS5.\r \r     All modes use FTS5 keyword search.\r     Sema", "file_type": "rationale", "source_file": "src\\gradata\\_query.py", "source_location": "L270"}], "edges": [{"source": "query", "target": "contextlib", "relation": "imports", "confidence": "EXTRACTED", "source_file": "src\\gradata\\_query.py", "source_location": "L8", "weight": 1.0}, {"source": "query", "target": "sqlite3", "relation": "imports", "confidence": "EXTRACTED", "source_file": "src\\gradata\\_query.py", "source_location": "L9", "weight": 1.0}, {"source": "query", "target": "datetime", "relation": "imports_from", "confidence": "EXTRACTED", "source_file": "src\\gradata\\_query.py", "source_location": "L10", "weight": 1.0}, {"source": "query", "target": "pathlib", "relation": "imports_from", "confidence": "EXTRACTED", "source_file": "src\\gradata\\_query.py", "source_location": "L11", "weight": 1.0}, {"source": "query", "target": "typing", "relation": "imports_from", "confidence": "EXTRACTED", "source_file": "src\\gradata\\_query.py", "source_location": "L12", "weight": 1.0}, {"source": "query", "target": "gradata_paths", "relation": "imports", "confidence": "EXTRACTED", "source_file": "src\\gradata\\_query.py", "source_location": "L14", "weight": 1.0}, {"source": "query", "target": "gradata_config", "relation": "imports_from", "confidence": "EXTRACTED", "source_file": "src\\gradata\\_query.py", "source_location": "L15", "weight": 1.0}, {"source": "query", "target": "gradata_paths", "relation": "imports_from", "confidence": "EXTRACTED", "source_file": "src\\gradata\\_query.py", "source_location": "L34", "weight": 1.0}, {"source": "query", "target": "query_ensure_fts_table", "relation": "contains", "confidence": "EXTRACTED", "source_file": "src\\gradata\\_query.py", "source_location": "L38", "weight": 1.0}, {"source": "query", "target": "query_fts_index", "relation": "contains", "confidence": "EXTRACTED", "source_file": "src\\gradata\\_query.py", "source_location": "L55", "weight": 1.0}, {"source": "query", "target": "query_fts_index_batch", "relation": "contains", "confidence": "EXTRACTED", "source_file": "src\\gradata\\_query.py", "source_location": "L73", "weight": 1.0}, {"source": "query", "target": "query_fts_rebuild", "relation": "contains", "confidence": "EXTRACTED", "source_file": "src\\gradata\\_query.py", "source_location": "L91", "weight": 1.0}, {"source": "query", "target": "query_fts_search", "relation": "contains", "confidence": "EXTRACTED", "source_file": "src\\gradata\\_query.py", "source_location": "L140", "weight": 1.0}, {"source": "query", "target": "query_detect_query_mode", "relation": "contains", "confidence": "EXTRACTED", "source_file": "src\\gradata\\_query.py", "source_location": "L178", "weight": 1.0}, {"source": "query", "target": "query_reciprocal_rank_fusion", "relation": "contains", "confidence": "EXTRACTED", "source_file": "src\\gradata\\_query.py", "source_location": "L195", "weight": 1.0}, {"source": "query", "target": "query_compute_recency_weight", "relation": "contains", "confidence": "EXTRACTED", "source_file": "src\\gradata\\_query.py", "source_location": "L214", "weight": 1.0}, {"source": "query", "target": "query_classify_confidence", "relation": "contains", "confidence": "EXTRACTED", "source_file": "src\\gradata\\_query.py", "source_location": "L227", "weight": 1.0}, {"source": "query", "target": "query_infer_memory_type", "relation": "contains", "confidence": "EXTRACTED", "source_file": "src\\gradata\\_query.py", "source_location": "L237", "weight": 1.0}, {"source": "query", "target": "query_get_memory_weight", "relation": "contains", "confidence": "EXTRACTED", "source_file": "src\\gradata\\_query.py", "source_location": "L257", "weight": 1.0}, {"source": "query", "target": "query_brain_search", "relation": "contains", "confidence": "EXTRACTED", "source_file": "src\\gradata\\_query.py", "source_location": "L264", "weight": 1.0}, {"source": "query_fts_index", "target": "query_ensure_fts_table", "relation": "calls", "confidence": "EXTRACTED", "source_file": "src\\gradata\\_query.py", "source_location": "L59", "weight": 1.0}, {"source": "query_fts_index_batch", "target": "query_ensure_fts_table", "relation": "calls", "confidence": "EXTRACTED", "source_file": "src\\gradata\\_query.py", "source_location": "L76", "weight": 1.0}, {"source": "query_fts_rebuild", "target": "query_ensure_fts_table", "relation": "calls", "confidence": "EXTRACTED", "source_file": "src\\gradata\\_query.py", "source_location": "L99", "weight": 1.0}, {"source": "query_fts_search", "target": "query_ensure_fts_table", "relation": "calls", "confidence": "EXTRACTED", "source_file": "src\\gradata\\_query.py", "source_location": "L144", "weight": 1.0}, {"source": "query_brain_search", "target": "query_detect_query_mode", "relation": "calls", "confidence": "EXTRACTED", "source_file": "src\\gradata\\_query.py", "source_location": "L277", "weight": 1.0}, {"source": "query_brain_search", "target": "query_fts_search", "relation": "calls", "confidence": "EXTRACTED", "source_file": "src\\gradata\\_query.py", "source_location": "L280", "weight": 1.0}, {"source": "query_brain_search", "target": "query_compute_recency_weight", "relation": "calls", "confidence": "EXTRACTED", "source_file": "src\\gradata\\_query.py", "source_location": "L286", "weight": 1.0}, {"source": "query_brain_search", "target": "query_infer_memory_type", "relation": "calls", "confidence": "EXTRACTED", "source_file": "src\\gradata\\_query.py", "source_location": "L287", "weight": 1.0}, {"source": "query_brain_search", "target": "query_get_memory_weight", "relation": "calls", "confidence": "EXTRACTED", "source_file": "src\\gradata\\_query.py", "source_location": "L288", "weight": 1.0}, {"source": "query_brain_search", "target": "query_classify_confidence", "relation": "calls", "confidence": "EXTRACTED", "source_file": "src\\gradata\\_query.py", "source_location": "L290", "weight": 1.0}, {"source": "query_rationale_1", "target": "query", "relation": "rationale_for", "confidence": "EXTRACTED", "source_file": "src\\gradata\\_query.py", "source_location": "L1", "weight": 1.0}, {"source": "query_rationale_270", "target": "query_brain_search", "relation": "rationale_for", "confidence": "EXTRACTED", "source_file": "src\\gradata\\_query.py", "source_location": "L270", "weight": 1.0}]}