{"nodes": [{"id": "lesson_discriminator", "label": "lesson_discriminator.py", "file_type": "code", "source_file": "src\\gradata\\enhancements\\lesson_discriminator.py", "source_location": "L1"}, {"id": "lesson_discriminator_importancesignal", "label": "ImportanceSignal", "file_type": "code", "source_file": "src\\gradata\\enhancements\\lesson_discriminator.py", "source_location": "L46"}, {"id": "enum", "label": "Enum", "file_type": "code", "source_file": "", "source_location": ""}, {"id": "lesson_discriminator_discriminatorconfig", "label": "DiscriminatorConfig", "file_type": "code", "source_file": "src\\gradata\\enhancements\\lesson_discriminator.py", "source_location": "L57"}, {"id": "lesson_discriminator_discriminatorverdict", "label": "DiscriminatorVerdict", "file_type": "code", "source_file": "src\\gradata\\enhancements\\lesson_discriminator.py", "source_location": "L83"}, {"id": "lesson_discriminator_signal_count", "label": "signal_count()", "file_type": "code", "source_file": "src\\gradata\\enhancements\\lesson_discriminator.py", "source_location": "L100"}, {"id": "lesson_discriminator_lessondiscriminator", "label": "LessonDiscriminator", "file_type": "code", "source_file": "src\\gradata\\enhancements\\lesson_discriminator.py", "source_location": "L104"}, {"id": "lesson_discriminator_lessondiscriminator_init", "label": ".__init__()", "file_type": "code", "source_file": "src\\gradata\\enhancements\\lesson_discriminator.py", "source_location": "L120"}, {"id": "lesson_discriminator_lessondiscriminator_evaluate", "label": ".evaluate()", "file_type": "code", "source_file": "src\\gradata\\enhancements\\lesson_discriminator.py", "source_location": "L123"}, {"id": "lesson_discriminator_lessondiscriminator_batch_evaluate", "label": ".batch_evaluate()", "file_type": "code", "source_file": "src\\gradata\\enhancements\\lesson_discriminator.py", "source_location": "L224"}, {"id": "lesson_discriminator_lessondiscriminator_filter_high_value", "label": ".filter_high_value()", "file_type": "code", "source_file": "src\\gradata\\enhancements\\lesson_discriminator.py", "source_location": "L238"}, {"id": "lesson_discriminator_rationale_1", "label": "Lesson Discriminator \u2014 Importance scoring for corrections/lessons.\r ============", "file_type": "rationale", "source_file": "src\\gradata\\enhancements\\lesson_discriminator.py", "source_location": "L1"}, {"id": "lesson_discriminator_rationale_47", "label": "Signals that indicate a lesson's importance.", "file_type": "rationale", "source_file": "src\\gradata\\enhancements\\lesson_discriminator.py", "source_location": "L47"}, {"id": "lesson_discriminator_rationale_58", "label": "Configuration for the lesson discriminator.\r \r     Attributes:\r         min_conf", "file_type": "rationale", "source_file": "src\\gradata\\enhancements\\lesson_discriminator.py", "source_location": "L58"}, {"id": "lesson_discriminator_rationale_84", "label": "Result of importance evaluation.\r \r     Attributes:\r         is_high_value: Whet", "file_type": "rationale", "source_file": "src\\gradata\\enhancements\\lesson_discriminator.py", "source_location": "L84"}, {"id": "lesson_discriminator_rationale_105", "label": "Evaluates whether a correction is worth graduating.\r \r     Adapted from EverOS's", "file_type": "rationale", "source_file": "src\\gradata\\enhancements\\lesson_discriminator.py", "source_location": "L105"}, {"id": "lesson_discriminator_rationale_134", "label": "Evaluate a correction's importance for graduation.\r \r         Args:", "file_type": "rationale", "source_file": "src\\gradata\\enhancements\\lesson_discriminator.py", "source_location": "L134"}, {"id": "lesson_discriminator_rationale_228", "label": "Evaluate multiple corrections at once.\r \r         Args:\r             corrections", "file_type": "rationale", "source_file": "src\\gradata\\enhancements\\lesson_discriminator.py", "source_location": "L228"}, {"id": "lesson_discriminator_rationale_242", "label": "Filter corrections to only high-value ones.\r \r         Returns:\r             Lis", "file_type": "rationale", "source_file": "src\\gradata\\enhancements\\lesson_discriminator.py", "source_location": "L242"}], "edges": [{"source": "lesson_discriminator", "target": "dataclasses", "relation": "imports_from", "confidence": "EXTRACTED", "source_file": "src\\gradata\\enhancements\\lesson_discriminator.py", "source_location": "L35", "weight": 1.0}, {"source": "lesson_discriminator", "target": "enum", "relation": "imports_from", "confidence": "EXTRACTED", "source_file": "src\\gradata\\enhancements\\lesson_discriminator.py", "source_location": "L36", "weight": 1.0}, {"source": "lesson_discriminator", "target": "lesson_discriminator_importancesignal", "relation": "contains", "confidence": "EXTRACTED", "source_file": "src\\gradata\\enhancements\\lesson_discriminator.py", "source_location": "L46", "weight": 1.0}, {"source": "lesson_discriminator_importancesignal", "target": "enum", "relation": "inherits", "confidence": "EXTRACTED", "source_file": "src\\gradata\\enhancements\\lesson_discriminator.py", "source_location": "L46", "weight": 1.0}, {"source": "lesson_discriminator", "target": "lesson_discriminator_discriminatorconfig", "relation": "contains", "confidence": "EXTRACTED", "source_file": "src\\gradata\\enhancements\\lesson_discriminator.py", "source_location": "L57", "weight": 1.0}, {"source": "lesson_discriminator", "target": "lesson_discriminator_discriminatorverdict", "relation": "contains", "confidence": "EXTRACTED", "source_file": "src\\gradata\\enhancements\\lesson_discriminator.py", "source_location": "L83", "weight": 1.0}, {"source": "lesson_discriminator", "target": "lesson_discriminator_signal_count", "relation": "contains", "confidence": "EXTRACTED", "source_file": "src\\gradata\\enhancements\\lesson_discriminator.py", "source_location": "L100", "weight": 1.0}, {"source": "lesson_discriminator", "target": "lesson_discriminator_lessondiscriminator", "relation": "contains", "confidence": "EXTRACTED", "source_file": "src\\gradata\\enhancements\\lesson_discriminator.py", "source_location": "L104", "weight": 1.0}, {"source": "lesson_discriminator_lessondiscriminator", "target": "lesson_discriminator_lessondiscriminator_init", "relation": "method", "confidence": "EXTRACTED", "source_file": "src\\gradata\\enhancements\\lesson_discriminator.py", "source_location": "L120", "weight": 1.0}, {"source": "lesson_discriminator_lessondiscriminator", "target": "lesson_discriminator_lessondiscriminator_evaluate", "relation": "method", "confidence": "EXTRACTED", "source_file": "src\\gradata\\enhancements\\lesson_discriminator.py", "source_location": "L123", "weight": 1.0}, {"source": "lesson_discriminator_lessondiscriminator", "target": "lesson_discriminator_lessondiscriminator_batch_evaluate", "relation": "method", "confidence": "EXTRACTED", "source_file": "src\\gradata\\enhancements\\lesson_discriminator.py", "source_location": "L224", "weight": 1.0}, {"source": "lesson_discriminator_lessondiscriminator", "target": "lesson_discriminator_lessondiscriminator_filter_high_value", "relation": "method", "confidence": "EXTRACTED", "source_file": "src\\gradata\\enhancements\\lesson_discriminator.py", "source_location": "L238", "weight": 1.0}, {"source": "lesson_discriminator_lessondiscriminator_init", "target": "lesson_discriminator_discriminatorconfig", "relation": "calls", "confidence": "EXTRACTED", "source_file": "src\\gradata\\enhancements\\lesson_discriminator.py", "source_location": "L121", "weight": 1.0}, {"source": "lesson_discriminator_lessondiscriminator_evaluate", "target": "lesson_discriminator_discriminatorverdict", "relation": "calls", "confidence": "EXTRACTED", "source_file": "src\\gradata\\enhancements\\lesson_discriminator.py", "source_location": "L216", "weight": 1.0}, {"source": "lesson_discriminator_lessondiscriminator_batch_evaluate", "target": "lesson_discriminator_lessondiscriminator_evaluate", "relation": "calls", "confidence": "EXTRACTED", "source_file": "src\\gradata\\enhancements\\lesson_discriminator.py", "source_location": "L236", "weight": 1.0}, {"source": "lesson_discriminator_lessondiscriminator_filter_high_value", "target": "lesson_discriminator_lessondiscriminator_evaluate", "relation": "calls", "confidence": "EXTRACTED", "source_file": "src\\gradata\\enhancements\\lesson_discriminator.py", "source_location": "L249", "weight": 1.0}, {"source": "lesson_discriminator_rationale_1", "target": "lesson_discriminator", "relation": "rationale_for", "confidence": "EXTRACTED", "source_file": "src\\gradata\\enhancements\\lesson_discriminator.py", "source_location": "L1", "weight": 1.0}, {"source": "lesson_discriminator_rationale_47", "target": "lesson_discriminator_importancesignal", "relation": "rationale_for", "confidence": "EXTRACTED", "source_file": "src\\gradata\\enhancements\\lesson_discriminator.py", "source_location": "L47", "weight": 1.0}, {"source": "lesson_discriminator_rationale_58", "target": "lesson_discriminator_discriminatorconfig", "relation": "rationale_for", "confidence": "EXTRACTED", "source_file": "src\\gradata\\enhancements\\lesson_discriminator.py", "source_location": "L58", "weight": 1.0}, {"source": "lesson_discriminator_rationale_84", "target": "lesson_discriminator_discriminatorverdict", "relation": "rationale_for", "confidence": "EXTRACTED", "source_file": "src\\gradata\\enhancements\\lesson_discriminator.py", "source_location": "L84", "weight": 1.0}, {"source": "lesson_discriminator_rationale_105", "target": "lesson_discriminator_lessondiscriminator", "relation": "rationale_for", "confidence": "EXTRACTED", "source_file": "src\\gradata\\enhancements\\lesson_discriminator.py", "source_location": "L105", "weight": 1.0}, {"source": "lesson_discriminator_rationale_134", "target": "lesson_discriminator_lessondiscriminator_evaluate", "relation": "rationale_for", "confidence": "EXTRACTED", "source_file": "src\\gradata\\enhancements\\lesson_discriminator.py", "source_location": "L134", "weight": 1.0}, {"source": "lesson_discriminator_rationale_228", "target": "lesson_discriminator_lessondiscriminator_batch_evaluate", "relation": "rationale_for", "confidence": "EXTRACTED", "source_file": "src\\gradata\\enhancements\\lesson_discriminator.py", "source_location": "L228", "weight": 1.0}, {"source": "lesson_discriminator_rationale_242", "target": "lesson_discriminator_lessondiscriminator_filter_high_value", "relation": "rationale_for", "confidence": "EXTRACTED", "source_file": "src\\gradata\\enhancements\\lesson_discriminator.py", "source_location": "L242", "weight": 1.0}]}